.clang-format
.gitignore
DEV.md
LICENSE
MANIFEST.in
README.md
pyproject.toml
setup.py
xmake.lua
./setup.py
./scripts/build_ntops.py
./scripts/format.py
./scripts/install.py
./scripts/python_test.py
./scripts/set_env.py
./src/infiniop/ninetoothed/build.py
./src/infiniop/ops/relu/ninetoothed/build.py
./test/infiniop/__init__.py
./test/infiniop/add.py
./test/infiniop/attention.py
./test/infiniop/causal_softmax.py
./test/infiniop/clip.py
./test/infiniop/conv.py
./test/infiniop/dequantize.py
./test/infiniop/gemm.py
./test/infiniop/mul.py
./test/infiniop/random_sample.py
./test/infiniop/rearrange.py
./test/infiniop/relu.py
./test/infiniop/rms_norm.py
./test/infiniop/rope.py
./test/infiniop/softplus.py
./test/infiniop/sub.py
./test/infiniop/swiglu.py
./test/infiniop/topkrouter.py
./test/infiniop-test/test_generate/__init__.py
./test/infiniop-test/test_generate/infiniop_test.py
./test/infiniop-test/test_generate/testcases/__init__.py
./test/infiniop-test/test_generate/testcases/add.py
./test/infiniop-test/test_generate/testcases/causal_softmax.py
./test/infiniop-test/test_generate/testcases/clip.py
./test/infiniop-test/test_generate/testcases/gemm.py
./test/infiniop-test/test_generate/testcases/mul.py
./test/infiniop-test/test_generate/testcases/random_sample.py
./test/infiniop-test/test_generate/testcases/rearrange.py
./test/infiniop-test/test_generate/testcases/rms_norm.py
./test/infiniop-test/test_generate/testcases/rope.py
./test/infiniop-test/test_generate/testcases/sub.py
./test/infiniop-test/test_generate/testcases/swiglu.py
./test/infiniop/libinfiniop/__init__.py
./test/infiniop/libinfiniop/datatypes.py
./test/infiniop/libinfiniop/devices.py
./test/infiniop/libinfiniop/liboperators.py
./test/infiniop/libinfiniop/op_register.py
./test/infiniop/libinfiniop/structs.py
./test/infiniop/libinfiniop/utils.py
.github/ISSUE_TEMPLATE/bug反馈.md
.github/ISSUE_TEMPLATE/功能开发.md
.github/workflows/build.yml
InfiniCore.egg-info/PKG-INFO
InfiniCore.egg-info/SOURCES.txt
InfiniCore.egg-info/dependency_links.txt
InfiniCore.egg-info/top_level.txt
include/infiniccl.h
include/infinicore.h
include/infinicore.hpp
