Metadata-Version: 2.4
Name: InfiniCore
Version: 0.1.0
Summary: InfiniCore 是一个跨平台统一编程工具集，为不同芯片平台的功能（包括计算、运行时、通信等）提供统一 C 语言接口。
Project-URL: Homepage, https://github.com/InfiniTensor/InfiniCore
Project-URL: Issues, https://github.com/InfiniTensor/InfiniCore/issues
Classifier: Programming Language :: Python :: 3
Classifier: License :: OSI Approved :: MIT License
Classifier: Operating System :: OS Independent
Requires-Python: >=3.10
License-File: LICENSE
Dynamic: license-file
